robby/__init__.py
robby/cli.py
robby/main.py
robby/txredisbayes.py
robby/utils.py
robby-0.5.5.dist-info/AUTHORS.rst
robby-0.5.5.dist-info/LICENSE
robby-0.5.5.dist-info/METADATA
robby-0.5.5.dist-info/WHEEL
robby-0.5.5.dist-info/entry_points.txt
robby-0.5.5.dist-info/top_level.txt
robby-0.5.5.dist-info/RECORD
