Metadata-Version: 2.1
Name: robby
Version: 0.5.5
Summary: Robby
Home-page: https://github.com/smn/robby
Author: Simon de Haan
Author-email: simon@praekeltfoundation.org
License: BSD
Keywords: robby
Platform: UNKNOWN
Classifier: Development Status :: 2 - Pre-Alpha
Classifier: Intended Audience :: Developers
Classifier: License :: OSI Approved :: ISC License (ISCL)
Classifier: Natural Language :: English
Classifier: Programming Language :: Python :: 2
Classifier: Programming Language :: Python :: 2.6
Classifier: Programming Language :: Python :: 2.7
Classifier: Programming Language :: Python :: 3
Classifier: Programming Language :: Python :: 3.3
Classifier: Programming Language :: Python :: 3.4
Requires-Dist: klein (==15.1.0)
Requires-Dist: txredisapi (==1.3)
Requires-Dist: click (==5.1)
Requires-Dist: hiredis (==0.2.0)
Requires-Dist: snowballstemmer (==1.2.1)
Requires-Dist: PyStemmer (==1.3.0)
